src/__init__.py
src/sdk.py
src/api/__init__.py
src/api/characters.py
src/api/movies.py
src/client/__init__.py
src/client/client.py
src/common/__init__.py
src/common/constants.py
src/common/exceptions.py
src/common/logger.py
src/common/singleton.py
src/common/utils.py
src/common/version.py
dvt_the_one_sdk-0.1.0.dist-info/METADATA
dvt_the_one_sdk-0.1.0.dist-info/WHEEL
dvt_the_one_sdk-0.1.0.dist-info/top_level.txt
dvt_the_one_sdk-0.1.0.dist-info/RECORD
