Metadata-Version: 2.1
Name: dvt-the-one-sdk
Version: 0.1.0
Summary: The Lord of the Rings SDK encapsulating https://the-one-api.dev/documentation
Author: Daniel Van Tassell
Author-email: danielvantassell@gmail.com
Requires-Dist: requests
Requires-Dist: setuptools
